headctools/Preprocessor.py
headctools/__init__.py
headctools/antspyregistration.py
headctools/cli.py
headctools/utilities.py
headctools/assets/__init__.py
headctools/assets/download/UNet.csv
headctools/assets/download/UNetSP.csv
headctools/assets/download/__init__.py
headctools/assets/imgs/brain-segmentation.png
headctools/assets/imgs/preprocessing-example.png
headctools/assets/imgs/skull-rec.png
headctools/assets/imgs/logo/bright-bg-stroke.png
headctools/assets/imgs/logo/bright-bg-stroke.svg
headctools/assets/imgs/logo/brightbg.png
headctools/assets/imgs/logo/brightbg.svg
headctools/assets/imgs/logo/dark-bg-stroke.png
headctools/assets/imgs/logo/dark-bg-stroke.svg
headctools/assets/imgs/logo/darkbg.png
headctools/assets/imgs/logo/darkbg.svg
headctools/tools/__init__.py
headctools/tools/classic_segmentation.py
headctools/tools/controller.py
headctools/tools/downloader.py
headctools/tools/editor.py
headctools/tools/flap_reconstruction.py
headctools/tools/offline_augmentation.py
headctools/tools/pca_rec.py
headctools/tools/plot_utils.py
headctools/tools/plot_volumes.py
headctools-0.21.dist-info/LICENSE
headctools-0.21.dist-info/METADATA
headctools-0.21.dist-info/WHEEL
headctools-0.21.dist-info/entry_points.txt
headctools-0.21.dist-info/top_level.txt
headctools-0.21.dist-info/RECORD
