Metadata-Version: 2.1
Name: headctools
Version: 0.21
Summary: A set of tools for preproccessing and performing brain segmentation and skull reconstruction on head CT images
Home-page: https://gitlab.com/matzkin/headctools
Author: ['Franco Matzkin']
Author-email: fmatzkin@sinc.unl.edu.ar
License: MIT
Keywords: headctools, deep-brain-extractor
Platform: UNKNOWN
Requires-Dist: numpy
Requires-Dist: torch
Requires-Dist: SimpleITK
Requires-Dist: pynrrd
Requires-Dist: medpy
Requires-Dist: raster-geometry
Requires-Dist: requests
Requires-Dist: typer
Requires-Dist: tensorboard
Requires-Dist: pandas
Requires-Dist: scikit-image
Requires-Dist: antspyx
